{
    "accounts": [
        {
            "name": "TFSA RBC",
            "cash": 1129,
            "stocks": [
                {
                    "exchange": "TSE",
                    "symbol": "VCN",
                    "shareCount": 200,
                    "managementFee": 0.18
                },
                {
                    "exchange": "TSE",
                    "symbol": "VXC",
                    "shareCount": 100,
                    "managementFee": 0.4
                },
                {
                    "exchange": "TSE",
                    "symbol": "VAB",
                    "shareCount": 52,
                    "managementFee": 0.11
                },
                {
                    "exchange": "TSE",
                    "symbol": "XEF",
                    "shareCount": 98,
                    "managementFee": 0.35
                }
            ]
        },
        {
            "name": "RBC US Investment",
            "cash": 192.12,
            "stocks": [
                {
                    "exchange": "NASDAQ",
                    "symbol": "MSFT",
                    "shareCount": 53,
                    "managementFee": 0
                },
                {
                    "exchange": "NASDAQ",
                    "symbol": "GOOG",
                    "shareCount": 16,
                    "managementFee": 0
                },
                {
                    "exchange": "NASDAQ",
                    "symbol": "AAPL",
                    "shareCount": 115,
                    "managementFee": 0
                }
            ]
        }
    ]
}